odoo/addons/storage_file/README.rst
odoo/addons/storage_file/__init__.py
odoo/addons/storage_file/__manifest__.py
odoo/addons/storage_file/controllers/__init__.py
odoo/addons/storage_file/controllers/main.py
odoo/addons/storage_file/data/ir_cron.xml
odoo/addons/storage_file/data/storage_backend.xml
odoo/addons/storage_file/i18n/it.po
odoo/addons/storage_file/i18n/storage_file.pot
odoo/addons/storage_file/models/__init__.py
odoo/addons/storage_file/models/ir_actions_report.py
odoo/addons/storage_file/models/storage_backend.py
odoo/addons/storage_file/models/storage_file.py
odoo/addons/storage_file/security/ir.model.access.csv
odoo/addons/storage_file/security/storage_file.xml
odoo/addons/storage_file/static/description/icon.png
odoo/addons/storage_file/tests/__init__.py
odoo/addons/storage_file/tests/test_storage_file.py
odoo/addons/storage_file/views/storage_backend_view.xml
odoo/addons/storage_file/views/storage_file_view.xml
odoo/addons/storage_file/wizards/__init__.py
odoo/addons/storage_file/wizards/replace_file.py
odoo14_addon_storage_file-14.0.2.4.1.dist-info/METADATA
odoo14_addon_storage_file-14.0.2.4.1.dist-info/WHEEL
odoo14_addon_storage_file-14.0.2.4.1.dist-info/top_level.txt
odoo14_addon_storage_file-14.0.2.4.1.dist-info/RECORD
